animatsne/__init__.py
animatsne/anim.py
animatsne/similarities.py
animatsne-1.0.1.dist-info/LICENSE
animatsne-1.0.1.dist-info/METADATA
animatsne-1.0.1.dist-info/WHEEL
animatsne-1.0.1.dist-info/top_level.txt
animatsne-1.0.1.dist-info/RECORD
